[
    {"position":{"latlng":{"lat":19.4716521,"lng":-99.1910301}},"nombre":"Red Barn Stores 3862-AZCAPOTZALCO"},
    {"position":{"latlng":{"lat":19.3638213,"lng":-99.28539549999999}},"nombre":"Red Barn Stores 3858-CUAJIMALPA"},
    {"position":{"latlng":{"lat":19.3379984,"lng":-99.1833365}},"nombre":"Red Barn Stores 2430-COPILCO"},
    {"position":{"latlng":{"lat":19.4503538,"lng":-99.2181777}},"nombre":"Red Barn Stores 2344-LOMAS"},
    {"position":{"latlng":{"lat":19.3084441,"lng":-99.6326996}},"nombre":"Red Barn Stores 5825-ALFREDO DEL MAZO"},
    {"position":{"latlng":{"lat":19.46967,"lng":-99.1165201}},"nombre":"Red Barn Stores 2345-TEPEYAC"},
    {"position":{"latlng":{"lat":19.380356,"lng":-99.1411184}},"nombre":"Red Barn Stores 2670-TLALPAN"},
    {"position":{"latlng":{"lat":19.2936435,"lng":-99.12525389999999}},"nombre":"Red Barn Stores 3857-VILLA COAPA"},
    {"position":{"latlng":{"lat":19.2528135,"lng":-99.1278389}},"nombre":"KAYCHEE 154-Xochimilco"},
    {"position":{"latlng":{"lat":19.3080043,"lng":-99.0597086}},"nombre":"Red Barn Stores 2347-TLAHUAC"},
    {"position":{"latlng":{"lat":19.5061811,"lng":-99.144543}},"nombre":"Red Barn Stores 3877-TORRES  LINDAVISTA"},
    {"position":{"latlng":{"lat":19.5311614,"lng":-99.1561665}},"nombre":"Red Barn Stores 3794-ACUEDUCTO DE GUADALUPE"},
    {"position":{"latlng":{"lat":19.4175696,"lng":-99.1057879}},"nombre":"Red Barn Stores 3872-BALBUENA"},
    {"position":{"latlng":{"lat":19.3686975,"lng":-99.1641264}},"nombre":"Red Barn Stores 3845-UNIVERSIDAD"},
    {"position":{"latlng":{"lat":19.2576994,"lng":-99.6203743}},"nombre":"Red Barn Stores 3790-METEPEC"},
    {"position":{"latlng":{"lat":19.4197536,"lng":-99.094181}},"nombre":"Red Barn Stores 3851-AEROPUERTO"},
    {"position":{"latlng":{"lat":19.3102884,"lng":-98.85577339999999}},"nombre":"La Tienda Especiál 1001-San Buenaventura"},
    {"position":{"latlng":{"lat":19.2810112,"lng":-99.639355}},"nombre":"Red Barn Stores 2343-TOLUCA"},
    {"position":{"latlng":{"lat":19.3047124,"lng":-98.95144549999999}},"nombre":"Red Barn Stores 1202-HORIZONTE"},
    {"position":{"latlng":{"lat":19.3064068,"lng":-99.18730939999999}},"nombre":"Red Barn Stores 3863-PERIFERICO SUR"},
    {"position":{"latlng":{"lat":19.6955987,"lng":-98.9792289}},"nombre":"Red Barn Stores 1171-SAN JOSE TECAMC"},
    {"position":{"latlng":{"lat":19.502978,"lng":-99.28281349999999}},"nombre":"KAYCHEE 18-UN-Atizapan"},
    {"position":{"latlng":{"lat":19.3672382,"lng":-99.7551647}},"nombre":"La Tienda Especiál 1829-Almoloya"},
    {"position":{"latlng":{"lat":19.5113353,"lng":-99.2729713}},"nombre":"Red Barn Stores 1032-LOMAS VERDES"},
    {"position":{"latlng":{"lat":19.5429269,"lng":-99.2140096}},"nombre":"Red Barn Stores 3854-PIRULES"},
    {"position":{"latlng":{"lat":19.288933,"lng":-99.69966939999999}},"nombre":"Red Barn Stores 5791-ZINACANTEPEC"},
    {"position":{"latlng":{"lat":19.3451697,"lng":-99.1818565}},"nombre":"Red Barn Stores 3848-TAXQUEÑA"},
    {"position":{"latlng":{"lat":19.644678,"lng":-99.10809789999999}},"nombre":"KAYCHEE 146-Coacalco"},
    {"position":{"latlng":{"lat":19.4088845,"lng":-99.0753637}},"nombre":"KAYCHEE 165-Zaragoza"},
    {"position":{"latlng":{"lat":19.6041649,"lng":-99.2778321}},"nombre":"Red Barn Stores 2643-NICOLAS ROMERO"},
    {"position":{"latlng":{"lat":19.4418438,"lng":-99.20686640000001}},"nombre":"KAYCHEE 232-UN-Polanco"},
    {"position":{"latlng":{"lat":19.5526956,"lng":-99.2475985}},"nombre":"Red Barn Stores 5855-LAS ALAMEDAS"},
    {"position":{"latlng":{"lat":19.5003075,"lng":-99.23134540000001}},"nombre":"Red Barn Stores 3847-SATELITE"},
    {"position":{"latlng":{"lat":19.4297407,"lng":-99.1447229}},"nombre":"KAYCHEE 129-Un-Buen Tono"},
    {"position":{"latlng":{"lat":19.3108844,"lng":-98.92513799999999}},"nombre":"La Tienda Especiál 1109-Ayotla"},
    {"position":{"latlng":{"lat":19.525216,"lng":-99.22673119999999}},"nombre":"KAYCHEE 236-UN-Mundo E *Satelite"},
    {"position":{"latlng":{"lat":19.3617203,"lng":-99.2834093}},"nombre":"Red Barn Stores 3850-ECHEGARAY"},
    {"position":{"latlng":{"lat":19.6217697,"lng":-98.93538799999999}},"nombre":"La Tienda Especiál 1828-Acolman"},
    {"position":{"latlng":{"lat":19.4160154,"lng":-98.9590735}},"nombre":"La Tienda Especiál 2736-Chimalhuacan Peñon"},
    {"position":{"latlng":{"lat":19.6505224,"lng":-99.2008075}},"nombre":"La Tienda Especiál 3871-Plaza Cuautitlán"},
    {"position":{"latlng":{"lat":19.5531212,"lng":-99.1938285}},"nombre":"Red Barn Stores 2041-TOLTECAS"},
    {"position":{"latlng":{"lat":19.6710245,"lng":-99.17420200000001}},"nombre":"La Tienda Especiál 3883-Melchor Ocampo"},
    {"position":{"latlng":{"lat":19.5618301,"lng":-99.0319067}},"nombre":"Red Barn Stores 1203-SUPER PLAZA ECATEPEC"},
    {"position":{"latlng":{"lat":19.2537337,"lng":-98.89418409999999}},"nombre":"La Tienda Especiál 2072-Portal Chalco"},
    {"position":{"latlng":{"lat":19.3012551,"lng":-99.199024}},"nombre":"Red Barn Stores 2219-JOROBAS"},
    {"position":{"latlng":{"lat":19.3465369,"lng":-99.0182456}},"nombre":"La Tienda Especiál 3916-Iztapalapa Norte"},
    {"position":{"latlng":{"lat":19.631612,"lng":-99.0898905}},"nombre":"Red Barn Stores 4018-SANTA MARÍA COACALCO"},
    {"position":{"latlng":{"lat":19.3213377,"lng":-99.22149399999999}},"nombre":"SuperStore 3837-LUIS CABRERA"},
    {"position":{"latlng":{"lat":19.6114318,"lng":-99.0039766}},"nombre":"La Tienda Especiál 2871-Viento Nuevo"},
    {"position":{"latlng":{"lat":19.4826445,"lng":-99.0360022}},"nombre":"KAYCHEE 260-UN-Neza 2 *Impulsora"},
    {"position":{"latlng":{"lat":19.5693175,"lng":-99.2531739}},"nombre":"KAYCHEE 111-UN-Nicolas Romero"},
    {"position":{"latlng":{"lat":19.8121013,"lng":-99.0466939}},"nombre":"La Tienda Especiál 1830-Arbolada los Sauces"},
    {"position":{"latlng":{"lat":19.7945975,"lng":-99.8818307}},"nombre":"La Tienda Especiál 1236-Atlacomulco"},
    {"position":{"latlng":{"lat":19.3577363,"lng":-99.19799599999999}},"nombre":"SuperStore 2829-CALZADA DE LOS LEONES"},
    {"position":{"latlng":{"lat":19.3817299,"lng":-99.16498910000001}},"nombre":"SuperStore 3839-GIRASOLES"},
    {"position":{"latlng":{"lat":19.3213273,"lng":-99.0943539}},"nombre":"KAYCHEE  175-Lomas Estrella"},
    {"position":{"latlng":{"lat":19.4438971,"lng":-99.1533394}},"nombre":"Red Barn Stores 3846-BUENAVISTA"},
    {"position":{"latlng":{"lat":19.7010427,"lng":-99.082684}},"nombre":"Red Barn Stores 1423-SANTA ELENA"},
    {"position":{"latlng":{"lat":19.3575148,"lng":-99.1952409}},"nombre":"Red Barn Stores 3852-PLATEROS"},
    {"position":{"latlng":{"lat":19.5308637,"lng":-99.1547882}},"nombre":"KAYCHEE 237-UN-Tenayuca"},
    {"position":{"latlng":{"lat":19.6649701,"lng":-99.1991142}},"nombre":"Red Barn Stores 4157-PERIFÉRICO CUAUTITLAN"},
    {"position":{"latlng":{"lat":19.3791572,"lng":-99.10206869999999}},"nombre":"KAYCHEE 121-Churubusco"},
    {"position":{"latlng":{"lat":19.375858,"lng":-98.99258640000001}},"nombre":"KAYCHEE 116-UN-Tepozan"},
    {"position":{"latlng":{"lat":19.6873423,"lng":-98.9893766}},"nombre":"La Tienda Especiál 3214-Chinampa"},
    {"position":{"latlng":{"lat":19.7890792,"lng":-99.056457}},"nombre":"La Tienda Especiál 1899-San Juan de la Labor"},
    {"position":{"latlng":{"lat":19.3190744,"lng":-98.93881309999999}},"nombre":"La Tienda Especiál 3296-Villas de Ayotla"},
    {"position":{"latlng":{"lat":19.499829,"lng":-99.04328869999999}},"nombre":"La Tienda Especiál 3753-Plaza Aragón"},
    {"position":{"latlng":{"lat":19.715134,"lng":-99.214829}},"nombre":"La Tienda Especiál 1870-Tepotzotlan"},
    {"position":{"latlng":{"lat":19.2675264,"lng":-99.1167876}},"nombre":"La Tienda Especiál 3778-Xochimilco"},
    {"position":{"latlng":{"lat":19.4894721,"lng":-99.0542151}},"nombre":"La Tienda Especiál 3777-Valle de Aragón "},
    {"position":{"latlng":{"lat":19.5876168,"lng":-99.0244118}},"nombre":"Red Barn Stores 5765-LAS AMERICAS "},
    {"position":{"latlng":{"lat":19.5189794,"lng":-98.8652244}},"nombre":"Red Barn Stores 1489-HIPERPLAZA TEXCOCO"},
    {"position":{"latlng":{"lat":34.0522342,"lng":-118.2436849}},"nombre":"La Tienda Especiál 3799-Ángeles Iztapalapa"},
    {"position":{"latlng":{"lat":19.4788485,"lng":-99.0530058}},"nombre":"La Tienda Especiál 3892-Av Central"},
    {"position":{"latlng":{"lat":19.5322061,"lng":-99.047824}},"nombre":"La Tienda Especiál 1201-San Agustín Ecatepec"},
    {"position":{"latlng":{"lat":19.569849,"lng":-99.04313069999999}},"nombre":"La Tienda Especiál 3888-Vía Morelos"},
    {"position":{"latlng":{"lat":19.6584121,"lng":-99.25104999999999}},"nombre":"La Tienda Especiál 1199-Tepojaco"},
    {"position":{"latlng":{"lat":19.3182372,"lng":-99.2111413}},"nombre":"SuperStore 3833-JARDINES"},
    {"position":{"latlng":{"lat":19.4083441,"lng":-98.9244265}},"nombre":"La Tienda Especiál 5730-Chicoloapan"},
    {"position":{"latlng":{"lat":19.4112893,"lng":-99.17126359999999}},"nombre":"SuperStore 3820-MICHOACÁN"},
    {"position":{"latlng":{"lat":19.5514091,"lng":-99.076155}},"nombre":"La Tienda Especiál 3020-Xalostoc"},
    {"position":{"latlng":{"lat":19.5204147,"lng":-99.2471034}},"nombre":"SuperStore 3824-ORADORES"},
    {"position":{"latlng":{"lat":19.474244,"lng":-99.2336196}},"nombre":"SuperStore 3629-ECHEGARAY"},
    {"position":{"latlng":{"lat":19.4056939,"lng":-99.1481837}},"nombre":"La Tienda Especiál 2767-Doctores"},
    {"position":{"latlng":{"lat":19.4224741,"lng":-99.2599365}},"nombre":"SuperStore 3844-BOSQUES DE MINAS"},
    {"position":{"latlng":{"lat":19.4798101,"lng":-99.0958739}},"nombre":"Red Barn Stores 4547-EDUARDO MOLINA"},
    {"position":{"latlng":{"lat":19.4408518,"lng":-99.1847365}},"nombre":"SuperStore 3025-PARQUES POLANCO"},
    {"position":{"latlng":{"lat":19.633751,"lng":-99.1845752}},"nombre":"Red Barn Stores 4154-PERINORTE"},
    {"position":{"latlng":{"lat":19.4955109,"lng":-99.2016738}},"nombre":"Red Barn Stores 1580-EL ROSARIO"},
    {"position":{"latlng":{"lat":19.3424414,"lng":-99.24815939999999}},"nombre":"SuperStore 5817-AXOMIATLA"},
    {"position":{"latlng":{"lat":19.3371592,"lng":-99.6054905}},"nombre":"Red Barn Stores 5702-SANTIN "},
    {"position":{"latlng":{"lat":19.6493537,"lng":-99.2120735}},"nombre":"Red Barn Stores 1834-PLAZA DEL LAGO"},
    {"position":{"latlng":{"lat":19.61804,"lng":-99.2437609}},"nombre":"KAYCHEE 167-Lago de Gpe"},
    {"position":{"latlng":{"lat":19.5070175,"lng":-99.26023959999999}},"nombre":"SuperStore 3838-LOMAS VERDES"},
    {"position":{"latlng":{"lat":19.367564,"lng":-99.25909399999999}},"nombre":"KAYCHEE 652-UN-Samara Santa Fe"},
    {"position":{"latlng":{"lat":19.4338095,"lng":-99.19012430000001}},"nombre":"SuperStore 3811-HORACIO"},
    {"position":{"latlng":{"lat":19.4345474,"lng":-99.110631}},"nombre":"KAYCHEE 241-UN-Anfora"},
    {"position":{"latlng":{"lat":-34.5869034,"lng":-68.14314139999999}},"nombre":"KAYCHEE 157-Tecamac II (Heroes)"},
    {"position":{"latlng":{"lat":19.8302751,"lng":-99.22800799999999}},"nombre":"La Tienda Especiál 1150-Huehuetoca"},
    {"position":{"latlng":{"lat":19.4070033,"lng":-99.2389719}},"nombre":"SuperStore 3829-BOSQUES DE LAS LOMAS"},
    {"position":{"latlng":{"lat":19.4026576,"lng":-99.1557833}},"nombre":"La Tienda Especiál 1161-Valle De Chalco"},
    {"position":{"latlng":{"lat":19.2528158,"lng":-98.8997927}},"nombre":"La Tienda Especiál 1634-Cuautzingo"},
    {"position":{"latlng":{"lat":19.6056201,"lng":-99.04589399999999}},"nombre":"Red Barn Stores 3503-ECATEPEC CENTRO"},
    {"position":{"latlng":{"lat":19.3445576,"lng":-99.1562025}},"nombre":"SuperStore 3831-COYOACAN"},
    {"position":{"latlng":{"lat":19.322927,"lng":-99.24744299999999}},"nombre":"SuperStore 3896-FTES. PEDREGAL"},
    {"position":{"latlng":{"lat":19.3840769,"lng":-99.1772948}},"nombre":"SuperStore 3834-INDIANA"},
    {"position":{"latlng":{"lat":19.6573646,"lng":-99.01023339999999}},"nombre":"KAYCHEE 107-UN-Ojo de Agua"},
    {"position":{"latlng":{"lat":19.415274,"lng":-99.17800849999999}},"nombre":"SuperStore 3809-PACHUCA"},
    {"position":{"latlng":{"lat":19.3229854,"lng":-99.1067216}},"nombre":"La Tienda Especiál 3897-La Virgen"},
    {"position":{"latlng":{"lat":19.6138614,"lng":-99.1805498}},"nombre":"La Tienda Especiál 5768-Cd Labor"},
    {"position":{"latlng":{"lat":19.6289666,"lng":-99.0400318}},"nombre":"Red Barn Stores 3016-MACRO PLAZA HEROES TEC."},
    {"position":{"latlng":{"lat":19.370048,"lng":-98.9606707}},"nombre":"La Tienda Especiál 5813-La Paz"},
    {"position":{"latlng":{"lat":19.3898856,"lng":-99.1757592}},"nombre":"SuperStore 3817-GEORGIA"}

]